{
  "updated_at": "2026-03-13T17:30:06.002Z",
  "decayed": {
    "bullish": 1546.5,
    "bearish": 1612.6,
    "neutral": 21757.1,
    "rawTotal": 52958,
    "bullishPercent": 6.21,
    "bearishPercent": 6.47
  },
  "signals": {
    "wsb": "HOLD",
    "inverse": "HOLD"
  },
  "daily": {
    "date": "2026-03-13",
    "bullishCount": 1282,
    "bearishCount": 1394,
    "neutralCount": 17261,
    "totalComments": 19937,
    "bullishPercent": 6.43,
    "bearishPercent": 6.99,
    "recommendation": "HOLD",
    "threadType": "daily"
  }
}