{
  "updated_at": "2026-03-25T16:30:06.155Z",
  "decayed": {
    "bullish": 1527.8,
    "bearish": 1658.8,
    "neutral": 22928.1,
    "rawTotal": 54003,
    "bullishPercent": 5.85,
    "bearishPercent": 6.35
  },
  "signals": {
    "wsb": "HOLD",
    "inverse": "HOLD"
  },
  "daily": {
    "date": "2026-03-25",
    "bullishCount": 1082,
    "bearishCount": 1182,
    "neutralCount": 15222,
    "totalComments": 17486,
    "bullishPercent": 6.19,
    "bearishPercent": 6.76,
    "recommendation": "HOLD",
    "threadType": "daily"
  }
}