{
  "updated_at": "2026-03-27T13:00:06.196Z",
  "decayed": {
    "bullish": 1261.1,
    "bearish": 1580.7,
    "neutral": 21452.2,
    "rawTotal": 61921,
    "bullishPercent": 5.19,
    "bearishPercent": 6.51
  },
  "signals": {
    "wsb": "PUTS",
    "inverse": "CALLS"
  },
  "daily": {
    "date": "2026-03-27",
    "bullishCount": 286,
    "bearishCount": 294,
    "neutralCount": 4729,
    "totalComments": 5309,
    "bullishPercent": 5.39,
    "bearishPercent": 5.54,
    "recommendation": "HOLD",
    "threadType": "daily"
  }
}