{
  "updated_at": "2026-04-08T13:30:06.631Z",
  "decayed": {
    "bullish": 2053.1,
    "bearish": 1947.4,
    "neutral": 30442.7,
    "rawTotal": 74288,
    "bullishPercent": 5.96,
    "bearishPercent": 5.65
  },
  "signals": {
    "wsb": "HOLD",
    "inverse": "HOLD"
  },
  "daily": {
    "date": "2026-04-08",
    "bullishCount": 466,
    "bearishCount": 476,
    "neutralCount": 5379,
    "totalComments": 6321,
    "bullishPercent": 7.37,
    "bearishPercent": 7.53,
    "recommendation": "HOLD",
    "threadType": "daily"
  }
}