{
  "updated_at": "2026-03-12T13:30:05.931Z",
  "decayed": {
    "bullish": 961.6,
    "bearish": 990.2,
    "neutral": 15725.5,
    "rawTotal": 48225,
    "bullishPercent": 5.44,
    "bearishPercent": 5.6
  },
  "signals": {
    "wsb": "HOLD",
    "inverse": "HOLD"
  },
  "daily": {
    "date": "2026-03-12",
    "bullishCount": 181,
    "bearishCount": 197,
    "neutralCount": 3475,
    "totalComments": 3853,
    "bullishPercent": 4.7,
    "bearishPercent": 5.11,
    "recommendation": "HOLD",
    "threadType": "daily"
  }
}