{
  "updated_at": "2026-04-06T16:00:05.890Z",
  "decayed": {
    "bullish": 1251,
    "bearish": 1273.6,
    "neutral": 17990.3,
    "rawTotal": 33753,
    "bullishPercent": 6.1,
    "bearishPercent": 6.21
  },
  "signals": {
    "wsb": "HOLD",
    "inverse": "HOLD"
  },
  "daily": {
    "date": "2026-04-06",
    "bullishCount": 841,
    "bearishCount": 932,
    "neutralCount": 12177,
    "totalComments": 13950,
    "bullishPercent": 6.03,
    "bearishPercent": 6.68,
    "recommendation": "CALLS",
    "threadType": "daily"
  }
}