{
  "updated_at": "2026-04-17T16:00:06.075Z",
  "decayed": {
    "bullish": 2455.5,
    "bearish": 1847.9,
    "neutral": 21819.1,
    "rawTotal": 51033,
    "bullishPercent": 9.4,
    "bearishPercent": 7.07
  },
  "signals": {
    "wsb": "CALLS",
    "inverse": "PUTS"
  },
  "daily": {
    "date": "2026-04-17",
    "bullishCount": 1915,
    "bearishCount": 1429,
    "neutralCount": 15723,
    "totalComments": 19067,
    "bullishPercent": 10.04,
    "bearishPercent": 7.49,
    "recommendation": "PUTS",
    "threadType": "daily"
  }
}