{
  "updated_at": "2026-04-10T19:30:05.858Z",
  "decayed": {
    "bullish": 1579.7,
    "bearish": 1499.8,
    "neutral": 19496,
    "rawTotal": 46013,
    "bullishPercent": 7,
    "bearishPercent": 6.64
  },
  "signals": {
    "wsb": "HOLD",
    "inverse": "HOLD"
  },
  "daily": {
    "date": "2026-04-10",
    "bullishCount": 1919,
    "bearishCount": 1629,
    "neutralCount": 20532,
    "totalComments": 24080,
    "bullishPercent": 7.97,
    "bearishPercent": 6.76,
    "recommendation": "PUTS",
    "threadType": "daily"
  }
}