{
  "updated_at": "2026-04-23T18:30:06.182Z",
  "decayed": {
    "bullish": 2077.1,
    "bearish": 2243.3,
    "neutral": 23582.5,
    "rawTotal": 53799,
    "bullishPercent": 7.44,
    "bearishPercent": 8.04
  },
  "signals": {
    "wsb": "HOLD",
    "inverse": "HOLD"
  },
  "daily": {
    "date": "2026-04-23",
    "bullishCount": 2038,
    "bearishCount": 2090,
    "neutralCount": 21672,
    "totalComments": 25800,
    "bullishPercent": 7.9,
    "bearishPercent": 8.1,
    "recommendation": "HOLD",
    "threadType": "daily"
  }
}