{
  "updated_at": "2026-03-11T14:00:05.966Z",
  "decayed": {
    "bullish": 1096.1,
    "bearish": 1050,
    "neutral": 16414.7,
    "rawTotal": 47983,
    "bullishPercent": 5.91,
    "bearishPercent": 5.66
  },
  "signals": {
    "wsb": "HOLD",
    "inverse": "HOLD"
  },
  "daily": {
    "date": "2026-03-11",
    "bullishCount": 329,
    "bearishCount": 337,
    "neutralCount": 5266,
    "totalComments": 5932,
    "bullishPercent": 5.55,
    "bearishPercent": 5.68,
    "recommendation": "HOLD",
    "threadType": "daily"
  }
}