{
  "updated_at": "2026-04-17T19:30:06.032Z",
  "decayed": {
    "bullish": 2337.7,
    "bearish": 1866.3,
    "neutral": 22046,
    "rawTotal": 49121,
    "bullishPercent": 8.91,
    "bearishPercent": 7.11
  },
  "signals": {
    "wsb": "CALLS",
    "inverse": "PUTS"
  },
  "daily": {
    "date": "2026-04-17",
    "bullishCount": 2967,
    "bearishCount": 2296,
    "neutralCount": 25488,
    "totalComments": 30751,
    "bullishPercent": 9.65,
    "bearishPercent": 7.47,
    "recommendation": "PUTS",
    "threadType": "daily"
  }
}