{
  "updated_at": "2026-04-29T11:30:05.887Z",
  "decayed": {
    "bullish": 844.9,
    "bearish": 778.2,
    "neutral": 10331.6,
    "rawTotal": 42128,
    "bullishPercent": 7.07,
    "bearishPercent": 6.51
  },
  "signals": {
    "wsb": "HOLD",
    "inverse": "HOLD"
  },
  "daily": {
    "date": "2026-04-29",
    "bullishCount": 44,
    "bearishCount": 25,
    "neutralCount": 504,
    "totalComments": 573,
    "bullishPercent": 7.68,
    "bearishPercent": 4.36,
    "recommendation": "PUTS",
    "threadType": "daily"
  }
}