{
  "updated_at": "2026-04-08T17:30:06.443Z",
  "decayed": {
    "bullish": 2416.3,
    "bearish": 2374.6,
    "neutral": 33239,
    "rawTotal": 74632,
    "bullishPercent": 6.35,
    "bearishPercent": 6.24
  },
  "signals": {
    "wsb": "HOLD",
    "inverse": "HOLD"
  },
  "daily": {
    "date": "2026-04-08",
    "bullishCount": 1755,
    "bearishCount": 1934,
    "neutralCount": 21818,
    "totalComments": 25507,
    "bullishPercent": 6.88,
    "bearishPercent": 7.58,
    "recommendation": "HOLD",
    "threadType": "daily"
  }
}